prober/__init__.py
prober/prober.py
USB_Prober-0.0.1.dist-info/METADATA
USB_Prober-0.0.1.dist-info/WHEEL
USB_Prober-0.0.1.dist-info/entry_points.txt
USB_Prober-0.0.1.dist-info/top_level.txt
USB_Prober-0.0.1.dist-info/RECORD
