Metadata-Version: 2.1
Name: USB-Prober
Version: 0.0.1
Summary: A lightweight script that lists all connected USB devices.
Home-page: https://github.com/Heimdall-Framework/usb-prober
Author: Ivan Zlatanov
Author-email: me@iv.an
License: UNKNOWN
Platform: UNKNOWN
Classifier: Programming Language :: Python :: 3
Classifier: License :: OSI Approved :: GNU General Public License v3 or later (GPLv3+)
Classifier: Operating System :: OS Independent
Requires-Python: >=3.4
